Metadata-Version: 1.1
Name: screenshotapi
Version: 1.1.3
Summary: Python API Client for Screenshotapi.io
Home-page: https://github.com/screenshotapi/screenshotapi-python
Author: Doug Kerwin
Author-email: dwkerwin@gmail.com
License: MIT
Keywords: screenshot
Platform: UNKNOWN
Classifier: Development Status :: 5 - Production/Stable
Classifier: Intended Audience :: Developers
Classifier: Natural Language :: English
Classifier: License :: OSI Approved :: MIT License
Classifier: Programming Language :: Python
Classifier: Programming Language :: Python :: 2.7
Classifier: Programming Language :: Python :: 3
Classifier: Programming Language :: Python :: 3.3
Classifier: Programming Language :: Python :: 3.4
Classifier: Programming Language :: Python :: 3.5
Classifier: Programming Language :: Python :: 3.6
